fastlanelogger/__init__.py
fastlanelogger/fastlanelogger.py
fastlanelogger-0.1.0.dist-info/METADATA
fastlanelogger-0.1.0.dist-info/WHEEL
fastlanelogger-0.1.0.dist-info/top_level.txt
fastlanelogger-0.1.0.dist-info/RECORD
