Metadata-Version: 2.1
Name: fastlanelogger
Version: 0.1.0
Requires-Dist: azure-kusto-data
Requires-Dist: azure-identity
Requires-Dist: azure-keyvault-secrets
Requires-Dist: pandas
